setup.py
bin/reddrip
reddrip/__init__.py
reddrip.egg-info/PKG-INFO
reddrip.egg-info/SOURCES.txt
reddrip.egg-info/dependency_links.txt
reddrip.egg-info/not-zip-safe
reddrip.egg-info/requires.txt
reddrip.egg-info/top_level.txt
reddrip/cli/__init__.py
reddrip/commands/__init__.py
reddrip/commands/run.py
reddrip/commands/stat.py
reddrip/ripper/__init__.py
reddrip/util/__init__.py
reddrip/util/config.py
reddrip/util/log.py
reddrip/util/parse.py