Metadata-Version: 1.1
Name: reddrip
Version: 1.2.2
Summary: Reddrip is Reddit subreddit picture ripper.
Home-page: https://github.com/kotnik/reddrip
Author: Nikola Kotur
Author-email: kotnick+python@gmail.com
License: UNKNOWN
Download-URL: https://github.com/kotnik/reddrip/archive/v1.1.tar.gz
Keywords: reddit crawler
Platform: any
Classifier: Programming Language :: Python
Classifier: Development Status :: 4 - Beta
Classifier: License :: OSI Approved :: GNU General Public License v3 or later (GPLv3+)
Classifier: Environment :: Console
Classifier: Topic :: Internet :: WWW/HTTP
